TCPIP/LS.py
TCPIP/__init__.py
TCPIPLS-2.1.dist-info/METADATA
TCPIPLS-2.1.dist-info/WHEEL
TCPIPLS-2.1.dist-info/top_level.txt
TCPIPLS-2.1.dist-info/RECORD
