Metadata-Version: 2.1
Name: TCPIPLS
Version: 2.1
Summary: Python connect to PLC LS
Author: Quangcha
Author-email: duyquangd4.bk@gmail.com
Keywords: PLC,protocol,LS electric
